{"py/object": "rasa.core.featurizers.tracker_featurizers.MaxHistoryTrackerFeaturizer", "state_featurizer": {"py/object": "rasa.core.featurizers.single_state_featurizer.SingleStateFeaturizer", "_default_feature_states": {"intent": {"affirm": 0, "back": 1, "bot_challenge": 2, "crediting_method": 3, "current_balance": 4, "deny": 5, "goodbye": 6, "greet": 7, "info_account": 8, "insert_username_login": 9, "insert_username_registration": 10, "login": 11, "monthly_report": 12, "multiple_play": 13, "new_play": 14, "nlu_fallback": 15, "out_of_scope": 16, "payment_method": 17, "periodic_report": 18, "registration": 19, "restart": 20, "session_start": 21, "show_username": 22, "single_play": 23, "weekly_report": 24}, "action_name": {"action_listen": 0, "action_restart": 1, "action_session_start": 2, "action_default_fallback": 3, "action_deactivate_loop": 4, "action_revert_fallback_events": 5, "action_default_ask_affirmation": 6, "action_default_ask_rephrase": 7, "action_two_stage_fallback": 8, "action_unlikely_intent": 9, "action_back": 10, "...": 11, "action_extract_slots": 12, "action_auth_user": 13, "utter_already_logged": 14, "utter_ask_choice": 15, "utter_ask_exist_account": 16, "utter_ask_info_account": 17, "utter_ask_login": 18, "utter_ask_multiple_choice": 19, "utter_ask_period": 20, "utter_ask_registration": 21, "utter_ask_single_choice": 22, "utter_confirm_multiple": 23, "utter_confirm_single": 24, "utter_confused_multiple": 25, "utter_confused_single": 26, "utter_did_that_help": 27, "utter_display_matches": 28, "utter_goodbye": 29, "utter_greet": 30, "utter_happy": 31, "utter_iamabot": 32, "utter_out_of_scope": 33, "utter_restart": 34, "utter_show_balance": 35, "utter_show_monthly_report": 36, "utter_show_payment_method": 37, "utter_show_username": 38, "utter_show_weekly_report": 39}, "entities": {"username": 0}, "slots": {"authenticated_0": 0, "authenticated_1": 1}, "active_loop": {}}, "action_texts": [], "entity_tag_specs": []}, "max_history": 10, "remove_duplicates": true}